arclio_rules/__init__.py
arclio_rules/main.py
arclio_rules/datamodels/client_chema.py
arclio_rules/datamodels/rule_schema.py
arclio_rules/routes/rules.py
arclio_rules/services/rule_fetching_service.py
arclio_rules/services/rule_indexing_service.py
arclio_rules/services/rule_saving_service.py
arclio_rules-0.5.6.dist-info/METADATA
arclio_rules-0.5.6.dist-info/WHEEL
arclio_rules-0.5.6.dist-info/entry_points.txt
arclio_rules-0.5.6.dist-info/licenses/LICENCE
arclio_rules-0.5.6.dist-info/RECORD
