Metadata-Version: 2.4
Name: arclio-rules
Version: 0.5.6
Summary: Arclio-rules mcp-server created using fastmcp 🚀
Project-URL: Homepage, https://github.com/Rizz-Buzz/arclio-rules
Project-URL: Repository, https://github.com/Rizz-Buzz/arclio-rules.git
Project-URL: Documentation, https://github.com/Rizz-Buzz/arclio-rules/blob/main/README.md
Project-URL: Issues, https://github.com/Rizz-Buzz/arclio-rules/issues
Author-email: Fisseha Estifanos <fisseha.estifanos@rizzbuzz.com>
License-Expression: MIT
License-File: LICENCE
Requires-Python: >=3.12.8
Requires-Dist: aiohttp>=3.11.18
Requires-Dist: elasticsearch>=9.0.1
Requires-Dist: fastapi-mcp>=0.3.4
Requires-Dist: fastapi>=0.115.12
Requires-Dist: fastmcp>=2.4.0
Requires-Dist: frontmatter>=3.0.8
Requires-Dist: gitpython>=3.1.44
Requires-Dist: loguru>=0.7.3
Requires-Dist: pydantic>=2.11.4
Requires-Dist: redis>=6.2.0
Requires-Dist: twine>=6.1.0
Requires-Dist: uvicorn>=0.34.2
